Metadata-Version: 1.1
Name: classificator
Version: 0.1.5
Summary: Text classification automation tool
Home-page: https://github.com/denver1117/classificator
Author: Evan Harris
Author-email: emitchellh@gmail.com
License: MIT
Download-URL: https://pypi.org/project/classificator/#files
Platform: UNKNOWN
